algo_beast_protocols/__init__.py
algo_beast_protocols/algorithm.py
algo_beast_protocols/broker.py
algo_beast_protocols/broker_manager.py
algo_beast_protocols/chart.py
algo_beast_protocols/config.py
algo_beast_protocols/session.py
algo_beast_protocols/store.py
algo_beast_protocols-0.1.1.dist-info/LICENSE
algo_beast_protocols-0.1.1.dist-info/METADATA
algo_beast_protocols-0.1.1.dist-info/WHEEL
algo_beast_protocols-0.1.1.dist-info/top_level.txt
algo_beast_protocols-0.1.1.dist-info/RECORD
