Metadata-Version: 2.1
Name: algo-beast-protocols
Version: 0.1.1
Summary: AlgoBeast Protocols
Home-page: https://github.com/krunaldodiya/algo-beast-protocols
Author: Krunal Dodiya
Author-email: kunal.dodiya1@gmail.com
Classifier: Programming Language :: Python :: 3
Classifier: Operating System :: OS Independent
License-File: LICENSE
Requires-Dist: requests
